nuumpy/A1.py
nuumpy/A2.py
nuumpy/A3.py
nuumpy/A4.py
nuumpy/A5.py
nuumpy/A6.py
nuumpy/B1.py
nuumpy/B3.py
nuumpy/B4.py
nuumpy/C1.py
nuumpy/C2.py
nuumpy/C3.py
nuumpy/DS1.py
nuumpy/DS10.py
nuumpy/DS2.py
nuumpy/DS3.py
nuumpy/DS4.py
nuumpy/DS5.py
nuumpy/DS6.py
nuumpy/DS7.py
nuumpy/DS8.py
nuumpy/DS9.py
nuumpy/__init__.py
nuumpy-0.69.691.dist-info/METADATA
nuumpy-0.69.691.dist-info/WHEEL
nuumpy-0.69.691.dist-info/top_level.txt
nuumpy-0.69.691.dist-info/RECORD
